email_extras/models.py
email_extras/__init__.py
email_extras/apps.py
email_extras/forms.py
email_extras/backends.py
email_extras/admin.py
email_extras/utils.py
email_extras/settings.py
email_extras/migrations/__init__.py
email_extras/migrations/0002_auto_20161103_0752.py
email_extras/migrations/0003_auto_20161103_0315.py
email_extras/migrations/0004_use_djangos_emailfield.py
email_extras/migrations/0001_initial.py
email_extras/templates/admin/email_extras/key/change_form.html
email_extras/templates/admin/email_extras/address/change_form.html
django_email_extras-0.3.4.dist-info/RECORD
django_email_extras-0.3.4.dist-info/metadata.json
django_email_extras-0.3.4.dist-info/WHEEL
django_email_extras-0.3.4.dist-info/DESCRIPTION.rst
django_email_extras-0.3.4.dist-info/top_level.txt
django_email_extras-0.3.4.dist-info/METADATA
