Metadata-Version: 1.1
Name: django-email-extras
Version: 0.3.4
Summary: A Django reusable app providing the ability to send PGP encrypted and multipart emails using the Django templating system.
Home-page: https://github.com/stephenmcd/django-email-extras
Author: Stephen McDonald
Author-email: steve@jupo.org
License: UNKNOWN
Platform: UNKNOWN
Classifier: Development Status :: 5 - Production/Stable
Classifier: Environment :: Web Environment
Classifier: Intended Audience :: Developers
Classifier: Operating System :: OS Independent
Classifier: Programming Language :: Python
Classifier: Programming Language :: Python :: 2.6
Classifier: Programming Language :: Python :: 2.7
Classifier: Programming Language :: Python :: 3
Classifier: Programming Language :: Python :: 3.3
Classifier: Framework :: Django
Classifier: Topic :: Communications :: Email
Classifier: Topic :: Security :: Cryptography
